<?xml version="1.0" encoding="UTF-8"?>
<weeklyartistchart user="Hirenj_au" from="1163937600" to="1164542400">
<artist>
    <name>The Black Keys</name>
    <mbid></mbid>
    <chartposition>1</chartposition>
    <playcount>21</playcount>
    <url>http://www.last.fm/music/The+Black+Keys</url>
</artist>
<artist>
    <name>Amos Lee</name>
    <mbid></mbid>
    <chartposition>2</chartposition>
    <playcount>12</playcount>
    <url>http://www.last.fm/music/Amos+Lee</url>
</artist>
<artist>
    <name>Ryan Adams &amp; the Cardinals</name>
    <mbid></mbid>
    <chartposition>2</chartposition>
    <playcount>12</playcount>
    <url>http://www.last.fm/music/Ryan%2BAdams%2B%2526%2Bthe%2BCardinals</url>
</artist>
<artist>
    <name>The Kooks</name>
    <mbid></mbid>
    <chartposition>4</chartposition>
    <playcount>11</playcount>
    <url>http://www.last.fm/music/The+Kooks</url>
</artist>
<artist>
    <name>Juliette &amp; The Licks</name>
    <mbid></mbid>
    <chartposition>5</chartposition>
    <playcount>10</playcount>
    <url>http://www.last.fm/music/Juliette%2B%2526%2BThe%2BLicks</url>
</artist>
<artist>
    <name>Wolfmother</name>
    <mbid></mbid>
    <chartposition>6</chartposition>
    <playcount>9</playcount>
    <url>http://www.last.fm/music/Wolfmother</url>
</artist>
<artist>
    <name>Atmosphere</name>
    <mbid></mbid>
    <chartposition>7</chartposition>
    <playcount>5</playcount>
    <url>http://www.last.fm/music/Atmosphere</url>
</artist>
<artist>
    <name>Ludwig van Beethoven</name>
    <mbid></mbid>
    <chartposition>8</chartposition>
    <playcount>2</playcount>
    <url>http://www.last.fm/music/Ludwig+van+Beethoven</url>
</artist>
<artist>
    <name>Solid Steel</name>
    <mbid></mbid>
    <chartposition>8</chartposition>
    <playcount>2</playcount>
    <url>http://www.last.fm/music/Solid+Steel</url>
</artist>
<artist>
    <name>daveslounge@gmail.com</name>
    <mbid></mbid>
    <chartposition>8</chartposition>
    <playcount>2</playcount>
    <url>http://www.last.fm/music/daveslounge%40gmail.com</url>
</artist>
<artist>
    <name>Goblin/Dialogue</name>
    <mbid></mbid>
    <chartposition>11</chartposition>
    <playcount>1</playcount>
    <url>http://www.last.fm/music/Goblin%252FDialogue</url>
</artist>
<artist>
    <name>I Monster</name>
    <mbid></mbid>
    <chartposition>11</chartposition>
    <playcount>1</playcount>
    <url>http://www.last.fm/music/I+Monster</url>
</artist>
<artist>
    <name>Björk</name>
    <mbid></mbid>
    <chartposition>11</chartposition>
    <playcount>1</playcount>
    <url>http://www.last.fm/music/Bj%C3%B6rk</url>
</artist>
<artist>
    <name>Ash</name>
    <mbid></mbid>
    <chartposition>11</chartposition>
    <playcount>1</playcount>
    <url>http://www.last.fm/music/Ash</url>
</artist>
<artist>
    <name>Kid Creole &amp; Coconuts</name>
    <mbid></mbid>
    <chartposition>11</chartposition>
    <playcount>1</playcount>
    <url>http://www.last.fm/music/Kid%2BCreole%2B%2526%2BCoconuts</url>
</artist>
<artist>
    <name>Triple J</name>
    <mbid></mbid>
    <chartposition>11</chartposition>
    <playcount>1</playcount>
    <url>http://www.last.fm/music/Triple+J</url>
</artist>
<artist>
    <name>Queen</name>
    <mbid></mbid>
    <chartposition>11</chartposition>
    <playcount>1</playcount>
    <url>http://www.last.fm/music/Queen</url>
</artist>
<artist>
    <name>The Eighties Matchbox B-Line Disaster</name>
    <mbid></mbid>
    <chartposition>11</chartposition>
    <playcount>1</playcount>
    <url>http://www.last.fm/music/The+Eighties+Matchbox+B-Line+Disaster</url>
</artist>
</weeklyartistchart>